grit_requester/__init__.py
grit_requester/config.py
grit_requester/domain.py
grit_requester/query.py
grit_requester/service.py
grit_requester-1.0.2.dist-info/METADATA
grit_requester-1.0.2.dist-info/WHEEL
grit_requester-1.0.2.dist-info/licenses/LICENSE
grit_requester-1.0.2.dist-info/RECORD
