Metadata-Version: 2.4
Name: grit_requester
Version: 1.0.2
Summary: Grit requester client for Python
Project-URL: Homepage, https://github.com/not-empty/grit-requester-python
Project-URL: Issues, https://github.com/not-empty/grit-requester-python/issues
Author-email: Not Empty Foundation <dev@not-empty.org>
License-File: LICENSE
Classifier: License :: OSI Approved :: GNU General Public License v3 (GPLv3)
Classifier: Operating System :: OS Independent
Classifier: Programming Language :: Python :: 3
Requires-Python: >=3.6.9
Requires-Dist: requests
